{
    "$schema": "https://json-schema.org/draft/2020-12/schema",
    "$id": "./fixed_joint.json",
    "title": "Fixed joint",
    "type": "object",
    "format": "grid-strict",
    "id": "conid",
    "properties": {
        "connectiontype": {
            "type": "string",
            "enum": [
                "fixed"
            ],
            "options": {
                "hidden": true
            }
        },
        "objtype": {
            "title": "Connection",
            "type": "string",
            "enum": [
                "Connection"
            ],
            "options": {
                "hidden": true
            }
        },
        "name": {
            "title": "Name",
            "type": "string",
            "options": {
                "hidden": false,
                "grid_columns": 4
            }
        },
        "parent": {
            "title": "Parent node",
            "type": "string",
            "options": {
                "hidden": false,
                "grid_columns": 4
            },
            "watch": {
                "node": "worldmodel.nodes"
            },
            "enumSource": [
                {
                    "source": "node",
                    "value": "{{item.name}}"
                }
            ]
        },
        "child": {
            "title": "Child node",
            "type": "string",
            "options": {
                "hidden": false,
                "grid_columns": 4,
                "grid_break": true
            },
            "watch": {
                "node": "worldmodel.nodes"
            },
            "enumSource": [
                {
                    "source": "node",
                    "value": "{{item.name}}"
                }
            ]
        },
        "origin-orientation": {
            "title": "Orientation",
            "description": "String representation of orientation of origin frame",
            "type": "string",
            "default": "EulerZYX(0,0,0)",
            "options": {
                "grid_columns": 3
            }
        },
        "origin-position": {
            "title": "Position",
            "description": "String representation of position of origin frame",
            "type": "string",
            "default": "[0,0,0]",
            "options": {
                "grid_columns": 3
            }
        },
        "origin": {
            "title": "Origin",
            "type": "array",
            "options": {
                "hidden": true
            }
        },
        "origin-string": {
            "title": "Array representation of origin",
            "type": "string",
            "template": "computePair",
            "watch": {
                "expr1": "conid.origin-orientation",
                "expr2": "conid.origin-position"
            },
            "options": {
                "grid_columns": 6,
                "grid-break": true,
                "hidden": false
            }
        }
    },
    "required": [
        "connectiontype",
        "objtype",
        "name",
        "parent",
        "child",
        "origin-orientation",
        "origin-position",
        "origin",
        "origin-string"
    ],
    "additionalProperties": false,
    "options": {
        "disable_collapse": true,
        "disable_edit_json": true,
        "disable_properties": true
    }
}